httrip/__init__.py
httrip/core.py
httrip/http.py
httrip/routing.py
httrip/state.py
httrip-0.1.0.dist-info/WHEEL
httrip-0.1.0.dist-info/METADATA
httrip-0.1.0.dist-info/RECORD
