Metadata-Version: 2.1
Name: httrip
Version: 0.1.0
Summary: Tiny proof-of-concept HTTP framework for Trio
License: MIT
Author: L3viathan
Author-email: git@l3vi.de
Requires-Python: >=3.6,<4.0
Classifier: License :: OSI Approved :: MIT License
Classifier: Programming Language :: Python :: 3
Classifier: Programming Language :: Python :: 3.6
Classifier: Programming Language :: Python :: 3.7
Classifier: Programming Language :: Python :: 3.8
Classifier: Programming Language :: Python :: 3.9
Requires-Dist: trio (>=0.18.0,<0.19.0)
